Classfile /D:/self-study/codes/self/book-code-effic/target/classes/com/qixiafei/book/code/effic/c7/Moniter.class
  Last modified 2019-7-3; size 1095 bytes
  MD5 checksum ceefb5d6361072e918f65f38f2ef6ec0
  Compiled from "Moniter.java"
public class com.qixiafei.book.code.effic.c7.Moniter
  minor version: 0
  major version: 52
  flags: ACC_PUBLIC, ACC_SUPER
Constant pool:
   #1 = Methodref          #10.#35        // java/lang/Object."<init>":()V
   #2 = Class              #36            // com/qixiafei/book/code/effic/c7/Moniter
   #3 = Methodref          #2.#35         // com/qixiafei/book/code/effic/c7/Moniter."<init>":()V
   #4 = Class              #37            // java/lang/Thread
   #5 = Class              #38            // com/qixiafei/book/code/effic/c7/Moniter$1
   #6 = Methodref          #5.#39         // com/qixiafei/book/code/effic/c7/Moniter$1."<init>":(Lcom/qixiafei/book/code/effic/c7/Moniter;)V
   #7 = Methodref          #4.#40         // java/lang/Thread."<init>":(Ljava/lang/Runnable;)V
   #8 = Methodref          #4.#41         // java/lang/Thread.start:()V
   #9 = Fieldref           #2.#42         // com/qixiafei/book/code/effic/c7/Moniter.i:I
  #10 = Class              #43            // java/lang/Object
  #11 = Utf8               InnerClasses
  #12 = Utf8               i
  #13 = Utf8               I
  #14 = Utf8               <init>
  #15 = Utf8               ()V
  #16 = Utf8               Code
  #17 = Utf8               LineNumberTable
  #18 = Utf8               LocalVariableTable
  #19 = Utf8               this
  #20 = Utf8               Lcom/qixiafei/book/code/effic/c7/Moniter;
  #21 = Utf8               main
  #22 = Utf8               ([Ljava/lang/String;)V
  #23 = Utf8               args
  #24 = Utf8               [Ljava/lang/String;
  #25 = Utf8               moniter
  #26 = Utf8               StackMapTable
  #27 = Class              #36            // com/qixiafei/book/code/effic/c7/Moniter
  #28 = Utf8               add
  #29 = Utf8               add2
  #30 = Class              #43            // java/lang/Object
  #31 = Class              #44            // java/lang/Throwable
  #32 = Utf8               <clinit>
  #33 = Utf8               SourceFile
  #34 = Utf8               Moniter.java
  #35 = NameAndType        #14:#15        // "<init>":()V
  #36 = Utf8               com/qixiafei/book/code/effic/c7/Moniter
  #37 = Utf8               java/lang/Thread
  #38 = Utf8               com/qixiafei/book/code/effic/c7/Moniter$1
  #39 = NameAndType        #14:#45        // "<init>":(Lcom/qixiafei/book/code/effic/c7/Moniter;)V
  #40 = NameAndType        #14:#46        // "<init>":(Ljava/lang/Runnable;)V
  #41 = NameAndType        #47:#15        // start:()V
  #42 = NameAndType        #12:#13        // i:I
  #43 = Utf8               java/lang/Object
  #44 = Utf8               java/lang/Throwable
  #45 = Utf8               (Lcom/qixiafei/book/code/effic/c7/Moniter;)V
  #46 = Utf8               (Ljava/lang/Runnable;)V
  #47 = Utf8               start
{
  static int i;
    descriptor: I
    flags: ACC_STATIC

  public com.qixiafei.book.code.effic.c7.Moniter();
    descriptor: ()V
    flags: ACC_PUBLIC
    Code:
      stack=1, locals=1, args_size=1
         0: aload_0
         1: invokespecial #1                  // Method java/lang/Object."<init>":()V
         4: return
      LineNumberTable:
        line 14: 0
      LocalVariableTable:
        Start  Length  Slot  Name   Signature
            0       5     0  this   Lcom/qixiafei/book/code/effic/c7/Moniter;

  public static void main(java.lang.String[]);
    descriptor: ([Ljava/lang/String;)V
    flags: ACC_PUBLIC, ACC_STATIC
    Code:
      stack=5, locals=3, args_size=1
         0: new           #2                  // class com/qixiafei/book/code/effic/c7/Moniter
         3: dup
         4: invokespecial #3                  // Method "<init>":()V
         7: astore_1
         8: iconst_0
         9: istore_2
        10: iload_2
        11: bipush        100
        13: if_icmpge     40
        16: new           #4                  // class java/lang/Thread
        19: dup
        20: new           #5                  // class com/qixiafei/book/code/effic/c7/Moniter$1
        23: dup
        24: aload_1
        25: invokespecial #6                  // Method com/qixiafei/book/code/effic/c7/Moniter$1."<init>":(Lcom/qixiafei/book/code/effic/c7/Moniter;)V
        28: invokespecial #7                  // Method java/lang/Thread."<init>":(Ljava/lang/Runnable;)V
        31: invokevirtual #8                  // Method java/lang/Thread.start:()V
        34: iinc          2, 1
        37: goto          10
        40: return
      LineNumberTable:
        line 17: 0
        line 18: 8
        line 19: 16
        line 24: 31
        line 18: 34
        line 26: 40
      LocalVariableTable:
        Start  Length  Slot  Name   Signature
           10      30     2     i   I
            0      41     0  args   [Ljava/lang/String;
            8      33     1 moniter   Lcom/qixiafei/book/code/effic/c7/Moniter;
      StackMapTable: number_of_entries = 2
        frame_type = 253 /* append */
          offset_delta = 10
          locals = [ class com/qixiafei/book/code/effic/c7/Moniter, int ]
        frame_type = 250 /* chop */
          offset_delta = 29

  public synchronized void add();
    descriptor: ()V
    flags: ACC_PUBLIC, ACC_SYNCHRONIZED
    Code:
      stack=2, locals=1, args_size=1
         0: getstatic     #9                  // Field i:I
         3: iconst_1
         4: iadd
         5: putstatic     #9                  // Field i:I
         8: return
      LineNumberTable:
        line 31: 0
        line 32: 8
      LocalVariableTable:
        Start  Length  Slot  Name   Signature
            0       9     0  this   Lcom/qixiafei/book/code/effic/c7/Moniter;

  public void add2();
    descriptor: ()V
    flags: ACC_PUBLIC
    Code:
      stack=2, locals=3, args_size=1
         0: aload_0
         1: dup
         2: astore_1
         3: monitorenter
         4: getstatic     #9                  // Field i:I
         7: iconst_1
         8: iadd
         9: putstatic     #9                  // Field i:I
        12: aload_1
        13: monitorexit
        14: goto          22
        17: astore_2
        18: aload_1
        19: monitorexit
        20: aload_2
        21: athrow
        22: return
      Exception table:
         from    to  target type
             4    14    17   any
            17    20    17   any
      LineNumberTable:
        line 34: 0
        line 35: 4
        line 37: 12
        line 38: 22
      LocalVariableTable:
        Start  Length  Slot  Name   Signature
            0      23     0  this   Lcom/qixiafei/book/code/effic/c7/Moniter;
      StackMapTable: number_of_entries = 2
        frame_type = 255 /* full_frame */
          offset_delta = 17
          locals = [ class com/qixiafei/book/code/effic/c7/Moniter, class java/lang/Object ]
          stack = [ class java/lang/Throwable ]
        frame_type = 250 /* chop */
          offset_delta = 4

  static {};
    descriptor: ()V
    flags: ACC_STATIC
    Code:
      stack=1, locals=0, args_size=0
         0: iconst_1
         1: putstatic     #9                  // Field i:I
         4: return
      LineNumberTable:
        line 28: 0
}
SourceFile: "Moniter.java"
InnerClasses:
     static #5; //class com/qixiafei/book/code/effic/c7/Moniter$1
